{"team":{"name":"Dallas Wings","abbreviation":"DAL","logo":"https://a.espncdn.com/i/teamlogos/wnba/500/dal.png","record":"0-0","standing":"5th in Western Conference Division","color":"002b5c"},"upcoming":[{"date_iso":"2026-04-30T23:00Z","date":"Thu, April 30th at 7:00 PM EDT","date_short":"4/30 - 7:00 PM EDT","day_of_week":"Thu","month":"April","month_num":4,"day_num":30,"year":2026,"opponent":"Indiana Fever","opp_short":"Fever","opp_abbr":"IND","opp_logo":"https://a.espncdn.com/i/teamlogos/wnba/500/ind.png","opp_record":"1-0","home_away":"away","is_home":false,"location":"Away","venue":"Gainbridge Fieldhouse","city":"Indianapolis, IN","status":"Scheduled","completed":false,"season_type":"Preseason","team_score":"","opp_score":"","result":"","score_display":"","preview":"Series starts 5/9. IND: \u274c\u274c\ud83d\udfe2\u274c\ud83d\udfe2. DAL: \u274c\u274c\u274c\u274c\ud83d\udfe2"},{"date_iso":"2026-05-03T23:00Z","date":"Sun, May 3rd at 7:00 PM EDT","date_short":"5/3 - 7:00 PM EDT","day_of_week":"Sun","month":"May","month_num":5,"day_num":3,"year":2026,"opponent":"Las Vegas Aces","opp_short":"Aces","opp_abbr":"LV","opp_logo":"https://a.espncdn.com/i/teamlogos/wnba/500/lv.png","opp_record":"0-0","home_away":"home","is_home":true,"location":"Home","venue":"Moody Center","city":"Austin, TX","status":"Scheduled","completed":false,"season_type":"Preseason","team_score":"","opp_score":"","result":"","score_display":""},{"date_iso":"2026-05-09T17:00Z","date":"Sat, May 9th at 1:00 PM EDT","date_short":"5/9 - 1:00 PM EDT","day_of_week":"Sat","month":"May","month_num":5,"day_num":9,"year":2026,"opponent":"Indiana Fever","opp_short":"Fever","opp_abbr":"IND","opp_logo":"https://a.espncdn.com/i/teamlogos/wnba/500/ind.png","opp_record":"1-0","home_away":"away","is_home":false,"location":"Away","venue":"Gainbridge Fieldhouse","city":"Indianapolis, IN","status":"Scheduled","completed":false,"season_type":"Regular Season","team_score":"","opp_score":"","result":"","score_display":""},{"date_iso":"2026-05-13T00:00Z","date":"Tue, May 12th at 8:00 PM EDT","date_short":"5/12 - 8:00 PM EDT","day_of_week":"Wed","month":"May","month_num":5,"day_num":12,"year":2026,"opponent":"Atlanta Dream","opp_short":"Dream","opp_abbr":"ATL","opp_logo":"https://a.espncdn.com/i/teamlogos/wnba/500/atl.png","opp_record":"0-0","home_away":"home","is_home":true,"location":"Home","venue":"College Park Center","city":"Arlington, TX","status":"Scheduled","completed":false,"season_type":"Regular Season","team_score":"","opp_score":"","result":"","score_display":""},{"date_iso":"2026-05-15T00:00Z","date":"Thu, May 14th at 8:00 PM EDT","date_short":"5/14 - 8:00 PM EDT","day_of_week":"Fri","month":"May","month_num":5,"day_num":14,"year":2026,"opponent":"Minnesota Lynx","opp_short":"Lynx","opp_abbr":"MIN","opp_logo":"https://a.espncdn.com/i/teamlogos/wnba/500/min.png","opp_record":"1-0","home_away":"home","is_home":true,"location":"Home","venue":"College Park Center","city":"Arlington, TX","status":"Scheduled","completed":false,"season_type":"Regular Season","team_score":"","opp_score":"","result":"","score_display":""},{"date_iso":"2026-05-19T00:00Z","date":"Mon, May 18th at 8:00 PM EDT","date_short":"5/18 - 8:00 PM EDT","day_of_week":"Tue","month":"May","month_num":5,"day_num":18,"year":2026,"opponent":"Washington Mystics","opp_short":"Mystics","opp_abbr":"WSH","opp_logo":"https://a.espncdn.com/i/teamlogos/wnba/500/wsh.png","opp_record":"0-1","home_away":"home","is_home":true,"location":"Home","venue":"College Park Center","city":"Arlington, TX","status":"Scheduled","completed":false,"season_type":"Regular Season","team_score":"","opp_score":"","result":"","score_display":""},{"date_iso":"2026-05-21T01:00Z","date":"Wed, May 20th at 9:00 PM EDT","date_short":"5/20 - 9:00 PM EDT","day_of_week":"Thu","month":"May","month_num":5,"day_num":20,"year":2026,"opponent":"Chicago Sky","opp_short":"Sky","opp_abbr":"CHI","opp_logo":"https://a.espncdn.com/i/teamlogos/wnba/500/chi.png","opp_record":"0-1","home_away":"away","is_home":false,"location":"Away","venue":"Wintrust Arena","city":"Chicago, IL","status":"Scheduled","completed":false,"season_type":"Regular Season","team_score":"","opp_score":"","result":"","score_display":""},{"date_iso":"2026-05-22T23:30Z","date":"Fri, May 22nd at 7:30 PM EDT","date_short":"5/22 - 7:30 PM EDT","day_of_week":"Fri","month":"May","month_num":5,"day_num":22,"year":2026,"opponent":"Atlanta Dream","opp_short":"Dream","opp_abbr":"ATL","opp_logo":"https://a.espncdn.com/i/teamlogos/wnba/500/atl.png","opp_record":"0-0","home_away":"away","is_home":false,"location":"Away","venue":"Gateway Center","city":"College Park, GA","status":"Scheduled","completed":false,"season_type":"Regular Season","team_score":"","opp_score":"","result":"","score_display":""},{"date_iso":"2026-05-24T19:30Z","date":"Sun, May 24th at 3:30 PM EDT","date_short":"5/24 - 3:30 PM EDT","day_of_week":"Sun","month":"May","month_num":5,"day_num":24,"year":2026,"opponent":"New York Liberty","opp_short":"Liberty","opp_abbr":"NY","opp_logo":"https://a.espncdn.com/i/teamlogos/wnba/500/ny.png","opp_record":"0-1","home_away":"away","is_home":false,"location":"Away","venue":"Barclays Center","city":"Brooklyn, NY","status":"Scheduled","completed":false,"season_type":"Regular Season","team_score":"","opp_score":"","result":"","score_display":""},{"date_iso":"2026-05-29T00:00Z","date":"Thu, May 28th at 8:00 PM EDT","date_short":"5/28 - 8:00 PM EDT","day_of_week":"Fri","month":"May","month_num":5,"day_num":28,"year":2026,"opponent":"Las Vegas Aces","opp_short":"Aces","opp_abbr":"LV","opp_logo":"https://a.espncdn.com/i/teamlogos/wnba/500/lv.png","opp_record":"0-0","home_away":"home","is_home":true,"location":"Home","venue":"College Park Center","city":"Arlington, TX","status":"Scheduled","completed":false,"season_type":"Regular Season","team_score":"","opp_score":"","result":"","score_display":""},{"date_iso":"2026-06-02T00:00Z","date":"Mon, June 1st at 8:00 PM EDT","date_short":"6/1 - 8:00 PM EDT","day_of_week":"Tue","month":"June","month_num":6,"day_num":1,"year":2026,"opponent":"Seattle Storm","opp_short":"Storm","opp_abbr":"SEA","opp_logo":"https://a.espncdn.com/i/teamlogos/wnba/500/sea.png","opp_record":"0-1","home_away":"home","is_home":true,"location":"Home","venue":"College Park Center","city":"Arlington, TX","status":"Scheduled","completed":false,"season_type":"Regular Season","team_score":"","opp_score":"","result":"","score_display":""},{"date_iso":"2026-06-06T02:00Z","date":"Fri, June 5th at 10:00 PM EDT","date_short":"6/5 - 10:00 PM EDT","day_of_week":"Sat","month":"June","month_num":6,"day_num":5,"year":2026,"opponent":"Los Angeles Sparks","opp_short":"Sparks","opp_abbr":"LA","opp_logo":"https://a.espncdn.com/i/teamlogos/wnba/500/la.png","opp_record":"1-0","home_away":"away","is_home":false,"location":"Away","venue":"crypto.com Arena","city":"Los Angeles, CA","status":"Scheduled","completed":false,"season_type":"Regular Season","team_score":"","opp_score":"","result":"","score_display":""},{"date_iso":"2026-06-10T00:00Z","date":"Tue, June 9th at 8:00 PM EDT","date_short":"6/9 - 8:00 PM EDT","day_of_week":"Wed","month":"June","month_num":6,"day_num":9,"year":2026,"opponent":"Minnesota Lynx","opp_short":"Lynx","opp_abbr":"MIN","opp_logo":"https://a.espncdn.com/i/teamlogos/wnba/500/min.png","opp_record":"1-0","home_away":"away","is_home":false,"location":"Away","venue":"Target Center","city":"Minneapolis, MN","status":"Scheduled","completed":false,"season_type":"Regular Season","team_score":"","opp_score":"","result":"","score_display":""},{"date_iso":"2026-06-12T01:00Z","date":"Thu, June 11th at 9:00 PM EDT","date_short":"6/11 - 9:00 PM EDT","day_of_week":"Fri","month":"June","month_num":6,"day_num":11,"year":2026,"opponent":"Phoenix Mercury","opp_short":"Mercury","opp_abbr":"PHX","opp_logo":"https://a.espncdn.com/i/teamlogos/wnba/500/phx.png","opp_record":"1-0","home_away":"home","is_home":true,"location":"Home","venue":"College Park Center","city":"Arlington, TX","status":"Scheduled","completed":false,"season_type":"Regular Season","team_score":"","opp_score":"","result":"","score_display":""},{"date_iso":"2026-06-14T00:30Z","date":"Sat, June 13th at 8:30 PM EDT","date_short":"6/13 - 8:30 PM EDT","day_of_week":"Sun","month":"June","month_num":6,"day_num":13,"year":2026,"opponent":"Portland Fire","opp_short":"Fire","opp_abbr":"POR","opp_logo":"https://a.espncdn.com/i/teamlogos/wnba/500/por.png","opp_record":"0-0","home_away":"away","is_home":false,"location":"Away","venue":"Moda Center","city":"Portland, OR","status":"Scheduled","completed":false,"season_type":"Regular Season","team_score":"","opp_score":"","result":"","score_display":""},{"date_iso":"2026-06-16T00:00Z","date":"Mon, June 15th at 8:00 PM EDT","date_short":"6/15 - 8:00 PM EDT","day_of_week":"Tue","month":"June","month_num":6,"day_num":15,"year":2026,"opponent":"Las Vegas Aces","opp_short":"Aces","opp_abbr":"LV","opp_logo":"https://a.espncdn.com/i/teamlogos/wnba/500/lv.png","opp_record":"0-0","home_away":"home","is_home":true,"location":"Home","venue":"College Park Center","city":"Arlington, TX","status":"Scheduled","completed":false,"season_type":"Regular Season","team_score":"","opp_score":"","result":"","score_display":""},{"date_iso":"2026-06-18T02:00Z","date":"Wed, June 17th at 10:00 PM EDT","date_short":"6/17 - 10:00 PM EDT","day_of_week":"Thu","month":"June","month_num":6,"day_num":17,"year":2026,"opponent":"Golden State Valkyries","opp_short":"Valkyries","opp_abbr":"GS","opp_logo":"https://a.espncdn.com/i/teamlogos/wnba/500/gs.png","opp_record":"1-0","home_away":"away","is_home":false,"location":"Away","venue":"Chase Center","city":"San Francisco, CA","status":"Scheduled","completed":false,"season_type":"Regular Season","team_score":"","opp_score":"","result":"","score_display":""},{"date_iso":"2026-06-21T00:00Z","date":"Sat, June 20th at 8:00 PM EDT","date_short":"6/20 - 8:00 PM EDT","day_of_week":"Sun","month":"June","month_num":6,"day_num":20,"year":2026,"opponent":"Chicago Sky","opp_short":"Sky","opp_abbr":"CHI","opp_logo":"https://a.espncdn.com/i/teamlogos/wnba/500/chi.png","opp_record":"0-1","home_away":"home","is_home":true,"location":"Home","venue":"College Park Center","city":"Arlington, TX","status":"Scheduled","completed":false,"season_type":"Regular Season","team_score":"","opp_score":"","result":"","score_display":""},{"date_iso":"2026-06-23T02:00Z","date":"Mon, June 22nd at 10:00 PM EDT","date_short":"6/22 - 10:00 PM EDT","day_of_week":"Tue","month":"June","month_num":6,"day_num":22,"year":2026,"opponent":"Seattle Storm","opp_short":"Storm","opp_abbr":"SEA","opp_logo":"https://a.espncdn.com/i/teamlogos/wnba/500/sea.png","opp_record":"0-1","home_away":"away","is_home":false,"location":"Away","venue":"Climate Pledge Arena","city":"Seattle, WA","status":"Scheduled","completed":false,"season_type":"Regular Season","team_score":"","opp_score":"","result":"","score_display":""},{"date_iso":"2026-06-26T02:00Z","date":"Thu, June 25th at 10:00 PM EDT","date_short":"6/25 - 10:00 PM EDT","day_of_week":"Fri","month":"June","month_num":6,"day_num":25,"year":2026,"opponent":"Las Vegas Aces","opp_short":"Aces","opp_abbr":"LV","opp_logo":"https://a.espncdn.com/i/teamlogos/wnba/500/lv.png","opp_record":"0-0","home_away":"away","is_home":false,"location":"Away","venue":"Michelob ULTRA Arena","city":"Las Vegas, NV","status":"Scheduled","completed":false,"season_type":"Regular Season","team_score":"","opp_score":"","result":"","score_display":""}],"next_game":{"date_iso":"2026-04-30T23:00Z","date":"Thu, April 30th at 7:00 PM EDT","date_short":"4/30 - 7:00 PM EDT","day_of_week":"Thu","month":"April","month_num":4,"day_num":30,"year":2026,"opponent":"Indiana Fever","opp_short":"Fever","opp_abbr":"IND","opp_logo":"https://a.espncdn.com/i/teamlogos/wnba/500/ind.png","opp_record":"1-0","home_away":"away","is_home":false,"location":"Away","venue":"Gainbridge Fieldhouse","city":"Indianapolis, IN","status":"Scheduled","completed":false,"season_type":"Preseason","team_score":"","opp_score":"","result":"","score_display":"","preview":"Series starts 5/9. IND: \u274c\u274c\ud83d\udfe2\u274c\ud83d\udfe2. DAL: \u274c\u274c\u274c\u274c\ud83d\udfe2"},"injuries":[{"name":"A. Kuier","position":"F","status":"Day-To-Day","detail":""},{"name":"C. Verona","position":"F","status":"Day-To-Day","detail":""},{"name":"J. Shepard","position":"F","status":"Day-To-Day","detail":""},{"name":"D. Fankam Mendjiadeu","position":"F","status":"Day-To-Day","detail":""},{"name":"A. Ogunbowale","position":"G","status":"Out","detail":""}],"calendars":[{"month_name":"April","month_num":4,"year":2026,"weeks":[[{"day":0,"has_game":false},{"day":0,"has_game":false},{"day":0,"has_game":false},{"day":1,"has_game":false},{"day":2,"has_game":false},{"day":3,"has_game":false},{"day":4,"has_game":false}],[{"day":5,"has_game":false},{"day":6,"has_game":false},{"day":7,"has_game":false},{"day":8,"has_game":false},{"day":9,"has_game":false},{"day":10,"has_game":false},{"day":11,"has_game":false}],[{"day":12,"has_game":false},{"day":13,"has_game":false},{"day":14,"has_game":false},{"day":15,"has_game":false},{"day":16,"has_game":false},{"day":17,"has_game":false},{"day":18,"has_game":false}],[{"day":19,"has_game":false},{"day":20,"has_game":false},{"day":21,"has_game":false},{"day":22,"has_game":false},{"day":23,"has_game":false},{"day":24,"has_game":false},{"day":25,"has_game":false}],[{"day":26,"has_game":false},{"day":27,"has_game":false},{"day":28,"has_game":false},{"day":29,"has_game":false},{"day":30,"has_game":true,"completed":false,"opp_abbr":"IND","home_away":"away","is_home":false,"time":"4/30 - 7:00 PM EDT"},{"day":0,"has_game":false},{"day":0,"has_game":false}]]},{"month_name":"May","month_num":5,"year":2026,"weeks":[[{"day":0,"has_game":false},{"day":0,"has_game":false},{"day":0,"has_game":false},{"day":0,"has_game":false},{"day":0,"has_game":false},{"day":1,"has_game":false},{"day":2,"has_game":false}],[{"day":3,"has_game":true,"completed":false,"opp_abbr":"LV","home_away":"home","is_home":true,"time":"5/3 - 7:00 PM EDT"},{"day":4,"has_game":false},{"day":5,"has_game":false},{"day":6,"has_game":false},{"day":7,"has_game":false},{"day":8,"has_game":false},{"day":9,"has_game":true,"completed":false,"opp_abbr":"IND","home_away":"away","is_home":false,"time":"5/9 - 1:00 PM EDT"}],[{"day":10,"has_game":false},{"day":11,"has_game":false},{"day":12,"has_game":true,"completed":false,"opp_abbr":"ATL","home_away":"home","is_home":true,"time":"5/12 - 8:00 PM EDT"},{"day":13,"has_game":false},{"day":14,"has_game":true,"completed":false,"opp_abbr":"MIN","home_away":"home","is_home":true,"time":"5/14 - 8:00 PM EDT"},{"day":15,"has_game":false},{"day":16,"has_game":false}],[{"day":17,"has_game":false},{"day":18,"has_game":true,"completed":false,"opp_abbr":"WSH","home_away":"home","is_home":true,"time":"5/18 - 8:00 PM EDT"},{"day":19,"has_game":false},{"day":20,"has_game":true,"completed":false,"opp_abbr":"CHI","home_away":"away","is_home":false,"time":"5/20 - 9:00 PM EDT"},{"day":21,"has_game":false},{"day":22,"has_game":true,"completed":false,"opp_abbr":"ATL","home_away":"away","is_home":false,"time":"5/22 - 7:30 PM EDT"},{"day":23,"has_game":false}],[{"day":24,"has_game":true,"completed":false,"opp_abbr":"NY","home_away":"away","is_home":false,"time":"5/24 - 3:30 PM EDT"},{"day":25,"has_game":false},{"day":26,"has_game":false},{"day":27,"has_game":false},{"day":28,"has_game":true,"completed":false,"opp_abbr":"LV","home_away":"home","is_home":true,"time":"5/28 - 8:00 PM EDT"},{"day":29,"has_game":false},{"day":30,"has_game":false}],[{"day":31,"has_game":false},{"day":0,"has_game":false},{"day":0,"has_game":false},{"day":0,"has_game":false},{"day":0,"has_game":false},{"day":0,"has_game":false},{"day":0,"has_game":false}]]},{"month_name":"June","month_num":6,"year":2026,"weeks":[[{"day":0,"has_game":false},{"day":1,"has_game":true,"completed":false,"opp_abbr":"SEA","home_away":"home","is_home":true,"time":"6/1 - 8:00 PM EDT"},{"day":2,"has_game":false},{"day":3,"has_game":false},{"day":4,"has_game":false},{"day":5,"has_game":true,"completed":false,"opp_abbr":"LA","home_away":"away","is_home":false,"time":"6/5 - 10:00 PM EDT"},{"day":6,"has_game":false}],[{"day":7,"has_game":false},{"day":8,"has_game":false},{"day":9,"has_game":true,"completed":false,"opp_abbr":"MIN","home_away":"away","is_home":false,"time":"6/9 - 8:00 PM EDT"},{"day":10,"has_game":false},{"day":11,"has_game":true,"completed":false,"opp_abbr":"PHX","home_away":"home","is_home":true,"time":"6/11 - 9:00 PM EDT"},{"day":12,"has_game":false},{"day":13,"has_game":true,"completed":false,"opp_abbr":"POR","home_away":"away","is_home":false,"time":"6/13 - 8:30 PM EDT"}],[{"day":14,"has_game":false},{"day":15,"has_game":true,"completed":false,"opp_abbr":"LV","home_away":"home","is_home":true,"time":"6/15 - 8:00 PM EDT"},{"day":16,"has_game":false},{"day":17,"has_game":true,"completed":false,"opp_abbr":"GS","home_away":"away","is_home":false,"time":"6/17 - 10:00 PM EDT"},{"day":18,"has_game":false},{"day":19,"has_game":false},{"day":20,"has_game":true,"completed":false,"opp_abbr":"CHI","home_away":"home","is_home":true,"time":"6/20 - 8:00 PM EDT"}],[{"day":21,"has_game":false},{"day":22,"has_game":true,"completed":false,"opp_abbr":"SEA","home_away":"away","is_home":false,"time":"6/22 - 10:00 PM EDT"},{"day":23,"has_game":false},{"day":24,"has_game":false},{"day":25,"has_game":true,"completed":false,"opp_abbr":"LV","home_away":"away","is_home":false,"time":"6/25 - 10:00 PM EDT"},{"day":26,"has_game":false},{"day":27,"has_game":false}],[{"day":28,"has_game":true,"completed":false,"opp_abbr":"MIN","home_away":"home","is_home":true,"time":"6/28 - 2:00 PM EDT"},{"day":29,"has_game":false},{"day":30,"has_game":false},{"day":0,"has_game":false},{"day":0,"has_game":false},{"day":0,"has_game":false},{"day":0,"has_game":false}]]}],"games_remaining":46,"total_games":46,"updated":"2026-04-26 08:32 UTC"}